langchain_utils/__init__.py
langchain_utils/config.py
langchain_utils/document_loaders.py
langchain_utils/get_clipboard_prompt.py
langchain_utils/get_html_prompt.py
langchain_utils/get_pandoc_prompt.py
langchain_utils/get_pdf_prompt.py
langchain_utils/get_text_prompt.py
langchain_utils/get_url_prompt.py
langchain_utils/get_word_prompt.py
langchain_utils/get_youtube_transcript_prompt.py
langchain_utils/job_search/config.py
langchain_utils/job_search/lcu_referral_statement.py
langchain_utils/job_search/prompts.py
langchain_utils/job_search/utils.py
langchain_utils/loaders.py
langchain_utils/prompts.py
langchain_utils/utils.py
langchain_utils/utils_argparse.py
langchain_utils/utils_doc_loaders.py
langchain_utils/utils_notify.py
langchain_utils-0.8.0.dist-info/METADATA
langchain_utils-0.8.0.dist-info/WHEEL
langchain_utils-0.8.0.dist-info/entry_points.txt
langchain_utils-0.8.0.dist-info/RECORD
