Metadata-Version: 2.1
Name: langchain-utils
Version: 0.8.0
Summary: Utilities built upon the langchain library
Home-page: https://github.com/tddschn/langchain-utils
License: MIT
Keywords: langchain,utils,LLM,prompts,CLI
Author: Teddy Xinyuan Chen
Author-email: 45612704+tddschn@users.noreply.github.com
Requires-Python: >=3.11,<4.0
Classifier: License :: OSI Approved :: MIT License
Classifier: Programming Language :: Python :: 3
Classifier: Programming Language :: Python :: 3.11
Classifier: Programming Language :: Python :: 3.12
Classifier: Topic :: Utilities
Requires-Dist: bs4 (>=0.0.1,<0.0.2)
Requires-Dist: langchain (>=0.0.351,<0.0.352)
Requires-Dist: langchain-core (==0.1.1)
Requires-Dist: markdownify (>=0.11.6,<0.12.0)
Requires-Dist: pymupdf (>=1.21.1,<2.0.0)
Requires-Dist: pync[notify] (>=2.0.3,<3.0.0)
Requires-Dist: pyperclip (>=1.8.2,<2.0.0)
Requires-Dist: pytube (>=15.0.0,<16.0.0)
Requires-Dist: selenium (>=4.8.3,<5.0.0)
Requires-Dist: tiktoken (>=0.3.3,<0.4.0)
Requires-Dist: tqdm (>=4.65.0,<5.0.0)
Requires-Dist: typing-extensions (==3.10.0.2)
Requires-Dist: unstructured (==0.5.2)
Requires-Dist: youtube-transcript-api (>=0.5.0,<0.6.0)
Project-URL: Bug Tracker, https://github.com/tddschn/langchain-utils/issues
Project-URL: Repository, https://github.com/tddschn/langchain-utils
